perfume/__init__.py
perfume/_version.py
perfume/analyze.py
perfume/colors.py
perfume/perfume.py
perfume_bench-0.1.6.dist-info/METADATA
perfume_bench-0.1.6.dist-info/RECORD
perfume_bench-0.1.6.dist-info/WHEEL
perfume_bench-0.1.6.dist-info/entry_points.txt
perfume_bench-0.1.6.dist-info/top_level.txt
