Metadata-Version: 2.1
Name: perfume-bench
Version: 0.1.6
Summary: Interactive performance benchmarking in Jupyter
Home-page: https://github.com/leifwalsh/perfume
Author: Leif Walsh
Author-email: leif.walsh@gmail.com
License: BSD license
Keywords: perfume python performance benchmarking jupyter interactive
Platform: UNKNOWN
Classifier: Development Status :: 2 - Pre-Alpha
Classifier: Intended Audience :: Developers
Classifier: License :: OSI Approved :: BSD License
Classifier: Natural Language :: English
Classifier: Programming Language :: Python :: 3
Classifier: Programming Language :: Python :: 3.4
Classifier: Programming Language :: Python :: 3.5
Classifier: Programming Language :: Python :: 3.6
Requires-Python: >=3.4, <4
Requires-Dist: bokeh (>=0.12)
Requires-Dist: ipython (>=5.0)
Requires-Dist: ipywidgets (>=5.0)
Requires-Dist: matplotlib (>=2.0)
Requires-Dist: notebook (>=5.0)
Requires-Dist: numpy (>=1.11)
Requires-Dist: pandas (>=0.19)
Requires-Dist: seaborn (>=0.7)
Requires-Dist: statsmodels (>=0.8)
